raruscloud/__init__.py
raruscloud/main.py
raruscloud-1.0.2.dist-info/METADATA
raruscloud-1.0.2.dist-info/WHEEL
raruscloud-1.0.2.dist-info/top_level.txt
raruscloud-1.0.2.dist-info/RECORD
