Metadata-Version: 2.1
Name: raruscloud
Version: 1.0.2
Summary: connector to rarus-cloud ESB
Home-page: UNKNOWN
Author: Serloz (Sergey Lozovskoy)
Author-email: <serloz@rarus.ru>
License: UNKNOWN
Keywords: python,esb,rarus
Platform: UNKNOWN
Classifier: Development Status :: 1 - Planning
Classifier: Intended Audience :: Developers
Classifier: Programming Language :: Python :: 3
Classifier: Operating System :: Unix
Classifier: Operating System :: MacOS :: MacOS X
Classifier: Operating System :: Microsoft :: Windows
Requires-Dist: loguru
Requires-Dist: requests
